LICENSE.txt
MANIFEST.in
README.md
setup.py
test.py
webspidy/__init__.py
webspidy/selector.py
webspidy.egg-info/PKG-INFO
webspidy.egg-info/SOURCES.txt
webspidy.egg-info/dependency_links.txt
webspidy.egg-info/requires.txt
webspidy.egg-info/top_level.txt